{"cameraMode":{"drawMode":0,"name":"Shaded","section":"Shading Mode"},"sceneLighting":true,"audioPlay":false,"sceneViewState":{"showFog":true,"showMaterialUpdate":false,"showSkybox":true,"showFlares":true,"showImageEffects":true,"showParticleSystems":true},"in2DMode":false,"pivot":{"x":-16.82880401611328,"y":3.735995292663574,"z":5.64735746383667},"rotation":{"x":0.10264050960540772,"y":0.08373411744832993,"z":0.008670641109347344,"w":-0.9911500215530396},"size":7.583106994628906,"orthographic":false}